iikocloudapi/__init__.py
iikocloudapi/api.py
iikocloudapi/client.py
iikocloudapi/helpers.py
iikocloudapi/modules/__init__.py
iikocloudapi/modules/auth.py
iikocloudapi/modules/dictionaries.py
iikocloudapi/modules/employees.py
iikocloudapi/modules/menu.py
iikocloudapi/modules/notifications.py
iikocloudapi/modules/operations.py
iikocloudapi/modules/organizations.py
iikocloudapi/modules/terminal_groups.py
iikocloudapi-0.4.0.dist-info/LICENCE
iikocloudapi-0.4.0.dist-info/METADATA
iikocloudapi-0.4.0.dist-info/WHEEL
iikocloudapi-0.4.0.dist-info/RECORD
