Metadata-Version: 2.1
Name: iikocloudapi
Version: 0.4.0
Summary: iikoCloud API async client
Home-page: https://github.com/ZeroFlowTech/iikocloudapi
License: MIT
Keywords: iiko,iikocloud,iiko-cloud,iiko-api,iikocloudapi,iiko-cloud-api,async,asyncio
Author: Deni Tazurkaev
Author-email: sha256deni@gmail.com
Requires-Python: >=3.11,<4.0
Classifier: Development Status :: 3 - Alpha
Classifier: Environment :: Console
Classifier: Intended Audience :: Developers
Classifier: License :: OSI Approved :: MIT License
Classifier: Programming Language :: Python :: 3
Classifier: Programming Language :: Python :: 3.11
Classifier: Programming Language :: Python :: 3.12
Classifier: Programming Language :: Python :: 3.13
Classifier: Programming Language :: Python :: 3 :: Only
Classifier: Topic :: Software Development :: Libraries :: Python Modules
Classifier: Typing :: Typed
Requires-Dist: httpx (>=0.28.1,<0.29.0)
Requires-Dist: orjson (>=3.10.15,<4.0.0)
Requires-Dist: pydantic (>=2.10.6,<3.0.0)
Project-URL: Bug Tracker, https://github.com/ZeroFlowTech/iikocloudapi/issues
Project-URL: Repository, https://github.com/ZeroFlowTech/iikocloudapi
